{
  "intents": [
    {
      "intent": "AMAZON.HelpIntent"
    },
    {
      "intent": "AMAZON.StopIntent"
    },
    {
      "intent": "AMAZON.CancelIntent"
    },
    {
      "intent": "DogParks"
    },
    {
      "intent": "RecommendPlace"
    },
    {
      "intent": "Festivals"
    },
    {
      "intent": "Events"
    },
    {
      "intent": "Brewery"
    },
    {
      "intent": "TrailPlaces"
    },
    {
      "intent": "RiverPlaces"
    },
    {
      "intent": "PoolPlaces"
    },
    {
      "intent": "EatGrass"
    },
    {
      "intent": "BuryBones"
    },
    {
      "intent": "Tick"
    },
    {
      "intent": "Shedding"
    },
    {
      "intent": "DogNoise"
    },
    {
      "intent": "Stop"
    },
    {
      "intent": "Open"
    },
    {
      "intent": "GetHelp"
    }
  ]
}
